racconfuncs/__init__.py
racconfuncs/racconfuncs.py
racconfuncs-1.0.7.dist-info/METADATA
racconfuncs-1.0.7.dist-info/WHEEL
racconfuncs-1.0.7.dist-info/top_level.txt
racconfuncs-1.0.7.dist-info/RECORD
