Metadata-Version: 2.4
Name: racconfuncs
Version: 1.0.7
Summary: Package for automating Raccon functions with Python based on Selenium
Author: l319836
Requires-Python: >=3.6
Requires-Dist: selenium>=4.0.0
Requires-Dist: requests>=2.25.0
Dynamic: author
Dynamic: description
Dynamic: description-content-type
Dynamic: requires-dist
Dynamic: requires-python
Dynamic: summary
